flask_optional_routes/__init__.py
flask_optional_routes/optional_routes.py
flask_optional_routes/route_branch.py
flask_optional_routes/route_branch_manager.py
flask_optional_routes-1.4.1.dist-info/METADATA
flask_optional_routes-1.4.1.dist-info/WHEEL
flask_optional_routes-1.4.1.dist-info/top_level.txt
flask_optional_routes-1.4.1.dist-info/RECORD
