Metadata-Version: 2.1
Name: flask-optional-routes
Version: 1.4.1
Summary: This package allows you to specify optional routes in a url path
Home-page: https://github.com/sudouser2010/flask_optional_routes
Author: Herbert Dawkins
Project-URL: Bug Tracker, https://github.com/sudouser2010/flask_optional_routes/issues
Classifier: Programming Language :: Python :: 3
Classifier: License :: OSI Approved :: MIT License
Classifier: Operating System :: OS Independent
Requires-Python: >=3.6
